stitchi/__init__.py
stitchi/app_config.json
stitchi/backend/__init__.py
stitchi/backend/classes.py
stitchi/main.py
stitchi-0.1.3.dist-info/METADATA
stitchi-0.1.3.dist-info/WHEEL
stitchi-0.1.3.dist-info/entry_points.txt
stitchi-0.1.3.dist-info/RECORD
