Metadata-Version: 2.1
Name: stitchi
Version: 0.1.3
Summary: cli video clipping tool
Author: mendozasho
Requires-Python: >=3.11,<4.0
Classifier: Programming Language :: Python :: 3
Classifier: Programming Language :: Python :: 3.11
Classifier: Programming Language :: Python :: 3.12
Requires-Dist: Dirlin (==0.1.15)
Requires-Dist: Pygments (==2.18.0)
Requires-Dist: click (==8.1.7)
Requires-Dist: et-xmlfile (==1.1.0)
Requires-Dist: ffmpeg-python (==0.2.0)
Requires-Dist: future (==1.0.0)
Requires-Dist: markdown-it-py (==3.0.0)
Requires-Dist: mdurl (==0.1.2)
Requires-Dist: python-dateutil (==2.9.0)
Requires-Dist: pytz (==2024.1)
Requires-Dist: rich (==13.7.1)
Requires-Dist: shellingham (==1.5.4)
Requires-Dist: six (==1.16.0)
Requires-Dist: typer (==0.12.3)
Requires-Dist: typing_extensions (==4.12.2)
Requires-Dist: tzdata (==2024.1)
